lambdalib/__init__.py
lambdalib/lambdalib.py
lambdalib/analoglib/__init__.py
lambdalib/analoglib/la_pll/la_pll.py
lambdalib/analoglib/la_pll/rtl/la_pll.v
lambdalib/analoglib/la_pll/testbench/la_pll_sim.v
lambdalib/analoglib/la_pll/testbench/tb_la_pll.v
lambdalib/analoglib/la_ring/la_ring.py
lambdalib/analoglib/la_ring/rtl/la_ring.v
lambdalib/auxlib/__init__.py
lambdalib/auxlib/la_antenna/la_antenna.py
lambdalib/auxlib/la_antenna/rtl/la_antenna.v
lambdalib/auxlib/la_clkicgand/la_clkicgand.py
lambdalib/auxlib/la_clkicgand/rtl/la_clkicgand.v
lambdalib/auxlib/la_clkicgor/la_clkicgor.py
lambdalib/auxlib/la_clkicgor/rtl/la_clkicgor.v
lambdalib/auxlib/la_clkmux2/la_clkmux2.py
lambdalib/auxlib/la_clkmux2/rtl/la_clkmux2.v
lambdalib/auxlib/la_clkmux2/testbench/tb_la_clkmux2.v
lambdalib/auxlib/la_clkmux4/la_clkmux4.py
lambdalib/auxlib/la_clkmux4/rtl/la_clkmux4.v
lambdalib/auxlib/la_decap/la_decap.py
lambdalib/auxlib/la_decap/rtl/la_decap.v
lambdalib/auxlib/la_drsync/la_drsync.py
lambdalib/auxlib/la_drsync/rtl/la_drsync.v
lambdalib/auxlib/la_dsync/la_dsync.py
lambdalib/auxlib/la_dsync/rtl/la_dsync.v
lambdalib/auxlib/la_footer/la_footer.py
lambdalib/auxlib/la_footer/rtl/la_footer.v
lambdalib/auxlib/la_header/la_header.py
lambdalib/auxlib/la_header/rtl/la_header.v
lambdalib/auxlib/la_ibuf/la_ibuf.py
lambdalib/auxlib/la_ibuf/rtl/la_ibuf.v
lambdalib/auxlib/la_iddr/la_iddr.py
lambdalib/auxlib/la_iddr/docs/iddr_waveform.json
lambdalib/auxlib/la_iddr/rtl/la_iddr.v
lambdalib/auxlib/la_idiff/la_idiff.py
lambdalib/auxlib/la_idiff/rtl/la_idiff.v
lambdalib/auxlib/la_isohi/la_isohi.py
lambdalib/auxlib/la_isohi/rtl/la_isohi.v
lambdalib/auxlib/la_isolo/la_isolo.py
lambdalib/auxlib/la_isolo/rtl/la_isolo.v
lambdalib/auxlib/la_keeper/la_keeper.py
lambdalib/auxlib/la_keeper/rtl/la_keeper.v
lambdalib/auxlib/la_obuf/la_obuf.py
lambdalib/auxlib/la_obuf/rtl/la_obuf.v
lambdalib/auxlib/la_oddr/la_oddr.py
lambdalib/auxlib/la_oddr/docs/oddr_waveform.json
lambdalib/auxlib/la_oddr/rtl/la_oddr.v
lambdalib-0.10.0.dist-info/licenses/LICENSE
lambdalib-0.10.0.dist-info/METADATA
lambdalib-0.10.0.dist-info/WHEEL
lambdalib-0.10.0.dist-info/top_level.txt
lambdalib-0.10.0.dist-info/RECORD
