Metadata-Version: 2.4
Name: lambdalib
Version: 0.10.0
Summary: Standardized ASIC design libraries
Author: Zero ASIC
License: MIT License
Project-URL: Homepage, https://github.com/siliconcompiler/lambdalib
Requires-Python: >=3.9
License-File: LICENSE
Requires-Dist: siliconcompiler>=0.35.0
Requires-Dist: Jinja2>=3.1.3
Provides-Extra: test
Requires-Dist: pytest==9.0.2; extra == "test"
Requires-Dist: pytest-xdist==3.8.0; extra == "test"
Requires-Dist: pytest-timeout==2.4.0; extra == "test"
Requires-Dist: cocotb==2.0.1; extra == "test"
Requires-Dist: cocotb-bus==0.3.0; extra == "test"
Provides-Extra: cocotb
Requires-Dist: cocotb==2.0.1; extra == "cocotb"
Requires-Dist: cocotb-bus==0.3.0; extra == "cocotb"
Provides-Extra: lint
Requires-Dist: flake8==7.3.0; extra == "lint"
Requires-Dist: codespell==2.4.1; extra == "lint"
Dynamic: license-file
